xds/__init__.py
xds/basic_use_of_xds_Python.py
xds/xds.py
xds-0.1.8.dist-info/LICENSE
xds-0.1.8.dist-info/METADATA
xds-0.1.8.dist-info/WHEEL
xds-0.1.8.dist-info/top_level.txt
xds-0.1.8.dist-info/RECORD
